firefox_tab_extractor/__init__.py
firefox_tab_extractor/cli.py
firefox_tab_extractor/exceptions.py
firefox_tab_extractor/extractor.py
firefox_tab_extractor/models.py
firefox_tab_extractor-1.0.0.dist-info/licenses/LICENSE
firefox_tab_extractor-1.0.0.dist-info/METADATA
firefox_tab_extractor-1.0.0.dist-info/WHEEL
firefox_tab_extractor-1.0.0.dist-info/entry_points.txt
firefox_tab_extractor-1.0.0.dist-info/top_level.txt
firefox_tab_extractor-1.0.0.dist-info/RECORD
