Metadata-Version: 2.4
Name: firefox-tab-extractor
Version: 1.0.0
Summary: A Python library to extract and organize Firefox browser tabs
Author-email: Vinicius Porto <vinicius.alves.porto@gmail.com>
Maintainer-email: Vinicius Porto <vinicius.alves.porto@gmail.com>
License: MIT
Project-URL: Homepage, https://github.com/ViniciusPuerto/firefox-tab-extractor
Project-URL: Documentation, https://github.com/ViniciusPuerto/firefox-tab-extractor#readme
Project-URL: Repository, https://github.com/ViniciusPuerto/firefox-tab-extractor
Project-URL: Bug Tracker, https://github.com/ViniciusPuerto/firefox-tab-extractor/issues
Project-URL: Discussions, https://github.com/ViniciusPuerto/firefox-tab-extractor/discussions
Keywords: firefox,browser,tabs,extraction,organization,productivity
Classifier: Development Status :: 4 - Beta
Classifier: Intended Audience :: Developers
Classifier: Intended Audience :: End Users/Desktop
Classifier: Operating System :: OS Independent
Classifier: Programming Language :: Python :: 3
Classifier: Programming Language :: Python :: 3.8
Classifier: Programming Language :: Python :: 3.9
Classifier: Programming Language :: Python :: 3.10
Classifier: Programming Language :: Python :: 3.11
Classifier: Topic :: Internet :: WWW/HTTP :: Browsers
Classifier: Topic :: Software Development :: Libraries :: Python Modules
Classifier: Topic :: Utilities
Requires-Python: >=3.7
License-File: LICENSE
Requires-Dist: lz4>=3.1.0
Provides-Extra: dev
Requires-Dist: pytest>=6.0; extra == "dev"
Requires-Dist: pytest-cov>=2.0; extra == "dev"
Requires-Dist: black>=21.0; extra == "dev"
Requires-Dist: flake8>=3.8; extra == "dev"
Requires-Dist: mypy>=0.800; extra == "dev"
Requires-Dist: pre-commit>=2.0; extra == "dev"
Dynamic: license-file
